smuploader/__init__.py
smuploader/smugmug.py
smuploader-0.3.2.data/scripts/smdownloader
smuploader-0.3.2.data/scripts/smregister
smuploader-0.3.2.data/scripts/smregtest
smuploader-0.3.2.data/scripts/smuploader
smuploader-0.3.2.dist-info/DESCRIPTION.rst
smuploader-0.3.2.dist-info/METADATA
smuploader-0.3.2.dist-info/RECORD
smuploader-0.3.2.dist-info/WHEEL
smuploader-0.3.2.dist-info/metadata.json
smuploader-0.3.2.dist-info/top_level.txt
