Metadata-Version: 2.0
Name: smuploader
Version: 0.3.2
Summary: A SmugMug uploader and downloader. Uses SmugMug API v2.0
Home-page: http://github.com/marekrei/smuploader
Author: Marek Rei, Erik Selberg
Author-email: marek@marekrei.com, erik@selberg.org
License: MIT
Platform: UNKNOWN
